hypixelv2_py-0.3.0.dist-info/licenses/LICENSE
hypy/__init__.py
hypy/exceptions.py
hypy/hypy.py
hypy/hypy_async.py
hypy/modals.py
hypixelv2_py-0.3.0.dist-info/METADATA
hypixelv2_py-0.3.0.dist-info/WHEEL
hypixelv2_py-0.3.0.dist-info/top_level.txt
hypixelv2_py-0.3.0.dist-info/RECORD
